{
    "ascent": [
        "Ascent_Lighting",
        "Ascent_Art_DefPathB",
        "Ascent_Gameplay_Dynamic",
        "Ascent_Art_VistaAtk",
        "Ascent_Art_Mid",
        "Ascent_Art_A",
        "Ascent_Art_B",
        "Ascent_Art_Env_VFX",
        "Ascent_Art_Atk",
        "Ascent_Art_Def",
        "Ascent_Volumes",
        "Ascent_Art_AtkPathA",
        "Ascent_Art_DefPathA",
        "Ascent_Art_AtkPathB",
        "Ascent_Art_APathMid",
        "Ascent_Art_VistaB",
        "Ascent_Art_VistaDef",
        "Ascent_Art_Vista",
        "Ascent_Gameplay",
        "Ascent_Art_VistaA",
        "Ascent_Mode_BombMode",
        "Ascent_TeamSpawnPoints",
        "Ascent_LightingBlockers",
        "Ascent"
    ],
    "split": [
        "Bonsai_Art_VistaB",
        "Bonsai_Volumes",
        "Bonsai_Art_DefPathB",
        "Bonsai_VFX",
        "Bonsai_Art_DefPathA",
        "Bonsai_Art_AtkPathA",
        "Bonsai_Art_B",
        "Bonsai_Art_AtkPathB",
        "Bonsai_Art_AtkSpawn",
        "Bonsai_Art_VistaAtk",
        "Bonsai_Art_VistaA",
        "Bonsai_Gameplay",
        "Bonsai_Art_VistaDef",
        "Bonsai_Art_MidVent",
        "Bonsai_Art_BTower",
        "Bonsai_Art_Sewer",
        "Bonsai_Art_MidConstruction",
        "Bonsai_Art_ATower",
        "Bonsai_Lighting",
        "Bonsai_Skybox",
        "Bonsai_Art_A",
        "Bonsai_Art_Mid",
        "Bonsai_Art_DefSpawn",
        "Bonsai_Gameplay_Dynamic",
        "Bonsai_Mode_BombMode",
        "Bonsai_TeamSpawnPoints",
        "Bonsai_SpawnBarrierVisuals",
        "Bonsai"
    ],
    "bind": [
        "Duality_Art_A",
        "Duality_Volumes",
        "Duality_Art_Def",
        "Duality_VFX",
        "Duality_Art_Vista",
        "Duality_Art_AtkPathA",
        "Duality_Art_AtkPathB",
        "Duality_Art_DefPathA",
        "Duality_Art_DefPathB",
        "Duality_Art_Mid",
        "Duality_Art_TPArrivalRooms",
        "Duality_Art_Signage",
        "Duality_Gameplay",
        "Duality_Art_MidPathB",
        "Duality_Art_MidPathA",
        "Duality_Art_Lantern",
        "Duality_Art_Destructibles",
        "Duality_Art_BathHouse",
        "Duality_Art_B",
        "Duality_Lighting",
        "Duality_Art_Atk",
        "Duality_BombGameMode_Only",
        "Duality_TeamSpawnPoints",
        "Duality_Skybox",
        "Duality_SpawnBarrier",
        "Duality"
    ],
    "breeze": [
        "Foxtrot_Art_AtkPath_A",
        "Foxtrot_Art_DefPath_B",
        "Foxtrot_Art_Vista",
        "Foxtrot_Art_AtkPath_B",
        "Foxtrot_Art_A_Tunnel",
        "Foxtrot_Art_DefPath_Mid",
        "Foxtrot_Art_Workshop",
        "Foxtrot_Art_VistaShip",
        "Foxtrot_Gameplay",
        "Foxtrot_Art_MidLower",
        "Foxtrot_Art_MidUpper",
        "Foxtrot_Art_VFX",
        "Foxtrot_Lighting",
        "Foxtrot_Art_A",
        "Foxtrot_Art_B",
        "Foxtrot_Art_Mid",
        "Foxtrot_Art_DefSpawn",
        "Foxtrot_Art_AtkSpawn",
        "Foxtrot_Mode_BombMode",
        "Foxtrot_TeamSpawnPoints",
        "Foxtrot"
    ],
    "icebox": [
        "Port_Art_AtkPathB",
        "Port_Art_DefPathB",
        "Port_Art_VistaA",
        "Port_Art_VistaB",
        "Port_Art_A",
        "Port_Art_VFX",
        "Port_Art_AtkSpawn",
        "Port_Art_B",
        "Port_Art_DefSpawn",
        "Port_Art_Mid",
        "Port_Art_Vista",
        "Port_Gameplay",
        "Port_TeamSpawnPoints",
        "Port_Lighting",
        "Port_Mode_BombMode",
        "Port"
    ],
    "haven": [
        "Triad_Gameplay",
        "Triad_Art_B",
        "Triad_Art_Atk",
        "Triad_Art_Def",
        "Triad_Art_Basalt",
        "Triad_Art_Vista",
        "Triad_Art_AtkPathA",
        "Triad_Art_AtkPathB",
        "Triad_Art_AtkPathC",
        "Triad_Art_Vista_Destruction",
        "Triad_Art_C_Destruction",
        "Triad_LightingDestruction",
        "Triad_Lighting",
        "Triad_Art_Destruction",
        "Triad_VFX",
        "Triad_Volumes",
        "Triad_Art_Skybox",
        "Triad_Art_A",
        "Triad_Mode_BombMode",
        "Triad_TeamSpawnPoints",
        "Triad_Art_Working",
        "Triad_Art_C",
        "Triad"
    ],
    "fracture": [
        "Canyon_Gameplay",
        "Canyon_BSiteTunnel",
        "Canyon_AtkPathToBSite",
        "Canyon_AtkSpawn",
        "Canyon_BackPath",
        "Canyon_VFX",
        "Canyon_BackPathtoA",
        "Canyon_Asite",
        "Canyon_VistaA",
        "Canyon_MidCollider",
        "Canyon_BSite",
        "Canyon_Mid",
        "Canyon_Lighting",
        "Canyon_BackPathToB",
        "Canyon_AtkPathToASite",
        "Canyon_ASidePath",
        "Canyon_TeamSpawnPoints",
        "Canyon_BombGameMode_Only",
        "Canyon_APathNoMid",
        "Canyon"
    ],
    "range": [
        "Range_Art_AsylumDown",
        "Range_Art_AsylumUp",
        "Range_Art_Tower",
        "Range_Art_VTOL",
        "Range_Art_Vegetation",
        "Range_Art_JumpCourse",
        "Range_Art_BMainInterior",
        "Range_VFX",
        "Range_Audio_Spatial",
        "Range_Art_Vista",
        "Range_Art_Bombsite",
        "Range_Art_AsylumBasement",
        "Range_Lighting",
        "Range_Gameplay",
        "Range_Art_Boathouse",
        "Range_Art_Bridge",
        "Range_Art_Cemetery",
        "Range_Art_Gallery",
        "Range_Art_Hospital",
        "Range_NPE_Only_Gameplay",
        "Range_Only_Gameplay",
        "Range_Art_Boathouse_ClientOnly_CosmeticDetails",
        "Range_Art_Bombsite_ClientOnly_CosmeticDetails",
        "Range_Art_Bridge_ClientOnly_CosmeticDetails",
        "Range_Art_Cemetery_ClientOnly_CosmeticDetails",
        "Range_Art_Gallery_ClientOnly_CosmeticDetails",
        "Range_Art_Hospital_ClientOnly_CosmeticDetails",
        "Range_Art_JumpCourse_ClientOnly_CosmeticDetails",
        "Range_Art_Tower_ClientOnly_CosmeticDetails",
        "Range_Art_Vegetation_ClientOnly_CosmeticDetails",
        "Range_Art_Vista_ClientOnly_CosmeticDetails",
        "Range_Art_JumpCourse_Outdated",
        "Range_Art_VTOL_ClientOnly_CosmeticDetails",
        "Range_ClientOnly",
        "Range_Art_AsylumDown_ClientOnly_CosmeticDetails",
        "Range_Art_AsylumUp_ClientOnly_CosmeticDetails",
        "Range_Art_BMainInterior_ClientOnly_CosmeticDetails",
        "Range_Profiling",
        "Range_Art_Boathouse_hide",
        "Range"
    ],
    "pearl": [
        "Pitt_Art_ASite",
        "Pitt_Art_Mid",
        "Pitt_Art_Vista",
        "Pitt_Art_DefPathB",
        "Pitt_Art_DefPathA",
        "Pitt_Art_AtkVista",
        "Pitt_Art_DefVista",
        "Pitt_Art_BVista",
        "Pitt_Art_VFX",
        "Pitt_Lighting",
        "Pitt_Art_AtkPathMid",
        "Pitt_Art_AtkPathMidToA",
        "Pitt_Art_Signage",
        "Pitt_Kill_Volumes",
        "Pitt_Gameplay",
        "Pitt_Art_DefSpawn",
        "Pitt_Art_BSite",
        "Pitt_Art_AtkSpawn",
        "Pitt_Art_AtkPathB",
        "Pitt_Art_AtkPathA",
        "Pitt_Mode_BombMode",
        "Pitt_TeamSpawnPoints",
        "Pitt"
    ],
    "character select": [
        "CharacterSelect_Ep02_01_EnvArt.umap",
        "CharacterSelect_Ep02_01_Lighting.umap"
    ],
    "menu": [
        "MainMenuV2",
        "MainMenu_Ep02_01_Lighting",
        "MainMenu_Ep02_01_EnvArt",
        "MainMenu_Ep02_01_Characters"
    ]
}